MANIFEST.in
NEWS.ja.rst
NEWS.rst
README.ja.rst
README.rst
setup.py
html/footer
html/footer.ja
html/index.html
html/index.html.ja
html/pikzie.css
lib/Pikzie.egg-info/PKG-INFO
lib/Pikzie.egg-info/SOURCES.txt
lib/Pikzie.egg-info/dependency_links.txt
lib/Pikzie.egg-info/top_level.txt
lib/pikzie/__init__.py
lib/pikzie/assertions.py
lib/pikzie/color.py
lib/pikzie/core.py
lib/pikzie/decorators.py
lib/pikzie/module_base.py
lib/pikzie/pretty_print.py
lib/pikzie/priority.py
lib/pikzie/report.py
lib/pikzie/results.py
lib/pikzie/tester.py
lib/pikzie/utils.py
lib/pikzie/ui/__init__.py
lib/pikzie/ui/console.py
license/lgpl.txt
po/ja.po
test/__init__.py
test/run-test.py
test/test_assertions.py
test/test_color.py
test/test_compatibility.py
test/test_data_driven_test.py
test/test_loader.py
test/test_metadata.py
test/test_module_based_test_case.py
test/test_priority.py
test/test_runner.py
test/test_utils.py
test/test_xml_report.py
test/utils.py
test/fixtures/__init__.py
test/fixtures/data_driven_test/__init__.py
test/fixtures/data_driven_test/test_data_driven_test_fixture.py
test/fixtures/module_based_test_cases/__init__.py
test/fixtures/module_based_test_cases/test_module_based_test_case_fixture.py
test/fixtures/tests/__init__.py
test/fixtures/tests/test_module_base.py
test/fixtures/tests/test_xxx.py
test/fixtures/tests/test_yyy.py
test/fixtures/tests/test_zzz.py