Metadata-Version: 1.1
Name: Pikzie
Version: 1.0.3
Summary: Pikzie is an easy to write/debug Unit Testing Framework for Python.
Home-page: http://pikzie.sourceforge.net/
Author: Kouhei Sutou
Author-email: kou@clear-code.com
License: LGPL
Download-URL: http://downloads.sourceforge.net/project/pikzie/pikzie/1.0.3/pikzie-1.0.3.tar.gz
Platform: UNKNOWN
Classifier: License :: OSI Approved :: GNU Library or Lesser General Public License (LGPL)
Classifier: Development Status :: 5 - Production/Stable
Classifier: Topic :: Software Development :: Testing
Classifier: Programming Language :: Python
Classifier: Programming Language :: Python :: 3
Classifier: Natural Language :: Japanese
Classifier: Natural Language :: English
